LICENSE
MANIFEST.in
README.md
setup.py
docs/cli.md
docs/csv.md
docs/install.md
docs/log.md
docs/sshclient.md
docs/utils.md
lambkid/__init__.py
lambkid/cli.py
lambkid.egg-info/PKG-INFO
lambkid.egg-info/SOURCES.txt
lambkid.egg-info/dependency_links.txt
lambkid.egg-info/entry_points.txt
lambkid.egg-info/requires.txt
lambkid.egg-info/top_level.txt
lambkid/libs/__init__.py
lambkid/libs/log.py
lambkid/libs/minio_client.py
lambkid/libs/ssh.py
lambkid/libs/utils.py